{
  "name": "Iceberg",
  "isDarkTheme": true,
  "background": "#161821",
  "backgroundFade": "#1E2132",
  "typeMain": "#C6C8D1",
  "typeSubtle": "#6B7089",
  "typeSubtlePlus": "#818596",
  "typeHighlight": "#2E313F",
  "typeLight": "#686F9A",
  "typeSuperlight": "#1E2132",
  "typeHyperLight": "#1E2132",
  "typeReverse": "#D8DEE9",
  "accent1Main": "#E27878",
  "accent1Secondary": "#E2A478",
  "accent1Tertiary": "#E2A478",
  "accent2Main": "#A093C7",
  "accent2Secondary": "#A093C7",
  "accent3Main": "#B4BE82",
  "accent3Secondary": "#B4BE82",
  "accent4Main": "#84A0C6",
  "accent4Secondary": "#84A0C6",
  "accent5Main": "#E27878",
  "accent5Secondary": "#E27878",
  "gridSuperlight": "#1E2132",
  "gridClear": "#1E2132",
  "gridBold": "#686F9A"
}